odoo/addons/base_video_link/README.rst
odoo/addons/base_video_link/__init__.py
odoo/addons/base_video_link/__manifest__.py
odoo/addons/base_video_link/data/video_provider_data.xml
odoo/addons/base_video_link/demo/video_demo.xml
odoo/addons/base_video_link/i18n/base_video_link.pot
odoo/addons/base_video_link/i18n/es_AR.po
odoo/addons/base_video_link/models/__init__.py
odoo/addons/base_video_link/models/video_link_mixin.py
odoo/addons/base_video_link/models/video_provider.py
odoo/addons/base_video_link/models/video_video.py
odoo/addons/base_video_link/readme/CONTRIBUTORS.rst
odoo/addons/base_video_link/readme/DESCRIPTION.rst
odoo/addons/base_video_link/readme/ROADMAP.rst
odoo/addons/base_video_link/readme/USAGE.rst
odoo/addons/base_video_link/security/ir.model.access.csv
odoo/addons/base_video_link/static/description/icon.png
odoo/addons/base_video_link/static/description/index.html
odoo/addons/base_video_link/tests/__init__.py
odoo/addons/base_video_link/tests/test_url.py
odoo/addons/base_video_link/views/menu_view.xml
odoo/addons/base_video_link/views/video_provider_view.xml
odoo/addons/base_video_link/views/video_video_view.xml
odoo14_addon_base_video_link-14.0.1.1.2.dist-info/METADATA
odoo14_addon_base_video_link-14.0.1.1.2.dist-info/WHEEL
odoo14_addon_base_video_link-14.0.1.1.2.dist-info/top_level.txt
odoo14_addon_base_video_link-14.0.1.1.2.dist-info/RECORD
